LICENSE
MANIFEST.in
README.md
pyproject.toml
setup.cfg
setup.py
versioneer.py
./docs/conf.py
./lholipop/__init__.py
./lholipop/_version.py
./lholipop/lholipop.py
./lholipop/data/log_theme.ini
./lholipop/io/__init__.py
./lholipop/test/conftest.py
./lholipop/test/test_basic.py
./lholipop/utils/__init__.py
./lholipop/utils/configuration.py
./lholipop/utils/file_utils.py
./lholipop/utils/logging.py
./lholipop/utils/package_data.py
lholipop/_version.py
lholipop.egg-info/PKG-INFO
lholipop.egg-info/SOURCES.txt
lholipop.egg-info/dependency_links.txt
lholipop.egg-info/requires.txt
lholipop.egg-info/top_level.txt
lholipop/data/log_theme.ini