Metadata-Version: 2.1
Name: lholipop
Version: 0.0.1
Summary: Python Boilerplate contains all the boilerplate you need to create a Python package.
Home-page: https://github.com/grburgess/lholipop
Author: J. Michael Burgess
Author-email: jburgess@mpe.mpg.de
License: GPL-2+
Project-URL: Bug Tracker, https://github.com/grburgess/lholipop/issues
Project-URL: Source Code, https://github.com/grburgess/lholipop
Classifier: Development Status :: 2 - Pre-Alpha
Classifier: Environment :: Console
Classifier: Intended Audience :: Science/Research
Classifier: License :: OSI Approved :: GNU General Public License v2 or later (GPLv2+)
Classifier: Operating System :: POSIX
Classifier: Programming Language :: Python :: 3.7
Classifier: Programming Language :: Python :: 3.8
Classifier: Programming Language :: Python :: 3.9
Classifier: Programming Language :: Python :: 3.10
Classifier: Topic :: Scientific/Engineering :: Physics
License-File: LICENSE
